requirementsengineering/__init__.py
requirementsengineering/__main__.py
requirementsengineering/main.py
requirementsengineering-0.1.2.dist-info/METADATA
requirementsengineering-0.1.2.dist-info/WHEEL
requirementsengineering-0.1.2.dist-info/entry_points.txt
requirementsengineering-0.1.2.dist-info/RECORD
