Metadata-Version: 2.3
Name: requirementsengineering
Version: 0.1.2
Summary: 
Author: Oce4nM4n
Author-email: ayushmansihag@gmail.com
Requires-Python: >=3.13
Classifier: Programming Language :: Python :: 3
Classifier: Programming Language :: Python :: 3.13
